honeymcp/__init__.py
honeymcp/cli.py
honeymcp/core/__init__.py
honeymcp/core/dynamic_ghost_tools.py
honeymcp/core/fingerprinter.py
honeymcp/core/ghost_tools.py
honeymcp/core/middleware.py
honeymcp/dashboard/__init__.py
honeymcp/dashboard/app.py
honeymcp/integrations/__init__.py
honeymcp/llm/__init__.py
honeymcp/llm/analyzers.py
honeymcp/llm/clients/__init__.py
honeymcp/llm/clients/provider_type.py
honeymcp/llm/prompts/__init__.py
honeymcp/llm/prompts/dynamic_ghost_tools.yaml
honeymcp/models/__init__.py
honeymcp/models/config.py
honeymcp/models/events.py
honeymcp/models/ghost_tool_spec.py
honeymcp/models/protection_mode.py
honeymcp/storage/__init__.py
honeymcp/storage/event_store.py
honeymcp-0.1.2.dist-info/METADATA
honeymcp-0.1.2.dist-info/WHEEL
honeymcp-0.1.2.dist-info/entry_points.txt
honeymcp-0.1.2.dist-info/licenses/LICENSE
honeymcp-0.1.2.dist-info/RECORD
