Metadata-Version: 2.4
Name: honeymcp
Version: 0.1.2
Summary: Deception middleware for AI agents - detecting data theft and indirect prompt injection in MCP servers
Project-URL: Homepage, https://github.com/barvhaim/HoneyMCP
Project-URL: Documentation, https://github.com/barvhaim/HoneyMCP#readme
Project-URL: Repository, https://github.com/barvhaim/HoneyMCP
Project-URL: Issues, https://github.com/barvhaim/HoneyMCP/issues
Project-URL: PyPI, https://pypi.org/project/honeymcp/
Author-email: Bar Haim <barha@il.ibm.com>, Alon Malach <Alon.Malach@ibm.com>
Maintainer-email: Bar Haim <barha@il.ibm.com>, Alon Malach <Alon.Malach@ibm.com>
License: Apache-2.0
License-File: LICENSE
Keywords: ai-security,data-exfiltration,deception,fastmcp,honeypot,mcp,model-context-protocol,prompt-injection,security
Classifier: Development Status :: 3 - Alpha
Classifier: Framework :: FastAPI
Classifier: Intended Audience :: Developers
Classifier: Intended Audience :: Information Technology
Classifier: Intended Audience :: System Administrators
Classifier: License :: OSI Approved :: Apache Software License
Classifier: Operating System :: OS Independent
Classifier: Programming Language :: Python :: 3
Classifier: Programming Language :: Python :: 3.11
Classifier: Programming Language :: Python :: 3.12
Classifier: Programming Language :: Python :: 3.13
Classifier: Topic :: Security
Classifier: Topic :: Software Development :: Libraries :: Python Modules
Requires-Python: >=3.11
Requires-Dist: aiofiles>=25.0.0
Requires-Dist: fastmcp>=3.0.0b1
Requires-Dist: langchain-ibm>=1.0.2
Requires-Dist: langchain-openai>=1.1.7
Requires-Dist: litellm>=1.0.0
Requires-Dist: mcp>=1.25.0
Requires-Dist: pydantic>=2.10.0
Requires-Dist: python-dateutil>=2.9.0
Requires-Dist: python-dotenv>=1.0.0
Requires-Dist: pyyaml>=6.0.0
Requires-Dist: requests>=2.32.0
Requires-Dist: rich>=14.0.0
Requires-Dist: starlette>=0.45.0
Requires-Dist: streamlit>=1.42.0
Requires-Dist: uvicorn>=0.34.0
